{
    "basics": {
      "name": "Brrayan Pérez",
      "label": "Software Developer with a focus on back-end development",
      "image": "/me.jpg",
      "email": "brrayanjavi@gmail.com",
      "phone": "+34 688888888",
      "url": "https://midu.dev",
      "summary": "Hi! I'm software developer with a focus on back-end development using Node.js with Express, and a strong foundation in both MongoDB and SQL databases. My proficiency extends to Android application development using Kotlin, having successfully created multiple applications.",
      "location": {
        "address": "",
        "postalCode": "80010",
        "city": "Curitiba",
        "countryCode": "BR",
        "country": "Brazil"
      },
      "profiles": [
        {
          "network": "LinkedIn",
          "username": "Brrayan Pérez",
          "url": "https://www.linkedin.com/in/brrayanperez/"
        },
        {
          "network": "GitHub",
          "username": "brrayancito",
          "url": "https://github.com/brrayancito"
        }
      ]
    },
    "work": [],
    "education": [{
      "institution": "Universidad Politécnica Territorial José Antonio Anzoátegui",
      "area": "Associate's degree in Computer Science",
      "studyType": "Associate",
      "startDate": "2014-08-01",
      "endDate": "2016-05-01"

    }],
    "certificates": [
      {
      "name": "Node.js, Express, MongoDB & More: The Complete Bootcamp 2023",
      "date": "2023-06-12",
      "issuer": "Udemy",
      "url": "https://www.udemy.com/certificate/UC-7b55528c-b3bb-4f69-95f2-99ff10b0f109/"
    },
    {
      "name": "The Complete JavaScript Course 2023: From Zero to Expert!",
      "date": "2023-03-20",
      "issuer": "Udemy",
      "url": "https://www.udemy.com/certificate/UC-74d1bb9c-bafc-4e8a-aefa-bfd52b695a71/"
    }
  ],
    "skills": [
      {
        "name": "Node.js",
        "keywords": [
          "Web Development", "Back-End", "API"
        ]
      },
      {
        "name": "JavaScript",
        "keywords": [
          "Web Development", "Front-End", "Back-End", "Fullstack"
        ]
      },
      {
        "name": "TypeScript",
        "keywords": [
          "Web Development", "Front-End", "Back-End"
        ]
      },
      {
        "name": "kotlin",
        "keywords": [
          "Android Development", "Back-End", "Android"
        ]
      },
      {
        "name": "MySQL",
        "keywords": [
          "Data Base", "SQL", "Back-End"
        ]
      },
      {
        "name": "MongoDB",
        "keywords": [
          "Data Base", "SQL", "Back-End"
        ]
      },
      {
        "name": "Git",
        "keywords": [
          "Version Control", "Code", "Cloud"
        ]
      },
      {
        "name": "GitHub",
        "keywords": [
          "Version Control", "Git"
        ]
      },
      {
        "name": "XML",
        "keywords": [
          "Mobile Development", "Android", "UI"
        ]
      },
      {
        "name": "React",
        "keywords": [
          "Web Development", "Front-End", "UI"
        ]
      }
    ],
    "languages": [
      {
        "language": "Spanish",
        "fluency": "Native speaker"
      },
      {
        "language": "English",
        "fluency": "Full professional proficiency"
      },
      {
        "language": "French",
        "fluency": "Professional working proficiency"
      },
      {
        "language": "Portuguese",
        "fluency": "Limited working proficiency"
      }
    ],
    "projects": [
      {
        "name": "Node.js API with Express, TypeScript, MongoDB...",
        "isActive": false,
        "description": "API built with Node.js, Express, and TypeScript. Implementing the Clean Architecture and Repository Pattern.",
        "highlights": [
          "Node.js",
          "MongoDB",
          "TypeScript",
          "Clean Architecture",
          "Repository Pattern"
        ],
        "github": "https://github.com/brrayancito/node-express-ts-clean"
      },
      {
        "name": "Christopher Nolan movies API",
        "isActive": true,
        "description": "Simple and efficient Christopher Nolan movies API",
        "highlights": [
          "API",
          "Node.js",
          "MongoDB",
          "Back-End"
        ],
        "url": "https://christopher-nolan-movies-api-dev-fehk.4.us-1.fl0.io/",
        "github": "https://github.com/brrayancito/christopher-nolan-movies-api"
      },
      {
        "name": "Christopher Nolan filmography",
        "isActive": true,
        "description": "Explore Nolan's cinematic universe with this page, powered by Astro",
        "highlights": [
          "Front-End",
          "JavaScript",
          "Astro"
        ],
        "url": "https://ch-nolan-filmography.vercel.app/movies",
        "github": "https://github.com/brrayancito/ch-nolan-filmography"
      },
      {
        "name": "Notes App",
        "isActive": true,
        "description": "The Notes App Website is a simple web application that allows users to create, read, update, and delete notes.",
        "highlights": [
          "Front-End",
          "EJS",
          "Google Authentication",
          "MongoDB"
        ],
        "url": "https://node-app-w1dw.onrender.com/",
        "github": "https://github.com/brrayancito/notes-app"
      }
    ]
  }